defconQt/__init__.py
defconQt/controls/__init__.py
defconQt/controls/baseCodeEditor.py
defconQt/controls/colorVignette.py
defconQt/controls/featureCodeEditor.py
defconQt/controls/glyphCellView.py
defconQt/controls/glyphContextView.py
defconQt/controls/glyphLineView.py
defconQt/controls/glyphNameComboBox.py
defconQt/controls/glyphSequenceEdit.py
defconQt/controls/glyphView.py
defconQt/controls/listView.py
defconQt/controls/roundedButtonSet.py
defconQt/representationFactories/__init__.py
defconQt/representationFactories/glyphCellFactory.py
defconQt/representationFactories/glyphViewFactory.py
defconQt/representationFactories/qPainterPathFactory.py
defconQt/tools/__init__.py
defconQt/tools/drawing.py
defconQt/tools/glyphsMimeData.py
defconQt/tools/platformSpecific.py
defconQt/tools/textSplitter.py
defconQt/windows/__init__.py
defconQt/windows/baseWindows.py
defconQt-0.5.4.dist-info/DESCRIPTION.rst
defconQt-0.5.4.dist-info/METADATA
defconQt-0.5.4.dist-info/RECORD
defconQt-0.5.4.dist-info/WHEEL
defconQt-0.5.4.dist-info/metadata.json
defconQt-0.5.4.dist-info/top_level.txt
