Metadata-Version: 2.0
Name: defconQt
Version: 0.5.4
Summary: A set of Qt objects for use in defcon applications.
Home-page: https://github.com/trufont/defconQt
Author: Adrien Tétar
Author-email: adri-from-59@hotmail.fr
License: GNU LGPL v3/GNU GPL v3
Platform: Win32
Platform: Mac OS X
Platform: Linux
Classifier: Development Status :: 4 - Beta
Classifier: Environment :: X11 Applications :: Qt
Classifier: Operating System :: MacOS :: MacOS X
Classifier: Operating System :: Microsoft :: Windows
Classifier: Operating System :: POSIX :: Linux
Classifier: Programming Language :: Python :: 3
Classifier: Intended Audience :: Developers
Classifier: Topic :: Text Processing :: Fonts
Classifier: Topic :: Multimedia :: Graphics :: Editors :: Vector-Based
Classifier: License :: OSI Approved :: GNU General Public License v3 (GPLv3)
Classifier: License :: OSI Approved :: GNU Lesser General Public License v3 (LGPLv3)
Requires-Dist: defcon (>=0.3.1)
Requires-Dist: fonttools (>=3.9.1)
Requires-Dist: pyqt5 (>=5.5.0)
Requires-Dist: ufoLib (>=2.0.0)
